gse_gsatmicro_mgr/__init__.py
gse_gsatmicro_mgr/__main__.py
gse_gsatmicro_mgr/common.py
gse_gsatmicro_mgr/con_server.py
gse_gsatmicro_mgr/ftp_server.py
gse_gsatmicro_mgr/gse_commands.py
gse_gsatmicro_mgr/http_server.py
gse_gsatmicro_mgr/quickfs.py
gse_gsatmicro_mgr/smp.py
gse_gsatmicro_mgr/smp_commands.py
gse_gsatmicro_mgr/smp_exceptions.py
gse_gsatmicro_mgr/terminal.py
gse_gsatmicro_mgr/vfs.py
gse_gsatmicro_mgr-5.5.0.dist-info/METADATA
gse_gsatmicro_mgr-5.5.0.dist-info/WHEEL
gse_gsatmicro_mgr-5.5.0.dist-info/entry_points.txt
gse_gsatmicro_mgr-5.5.0.dist-info/licenses/LICENSE.md
gse_gsatmicro_mgr-5.5.0.dist-info/RECORD
