Metadata-Version: 2.4
Name: gse-gsatmicro-mgr
Version: 5.5.0
Summary: Tools for interacting with GSatMicro Core products
Project-URL: homepage, https://www.gsat.us
Author-email: Bogdan Marinescu <bogdan@gsat.us>
License-File: LICENSE.md
Requires-Python: >=3.10
Requires-Dist: cbor2>=5.6.5
Requires-Dist: click>=8.1.0
Requires-Dist: crc>=7.0.0
Requires-Dist: flask>=3.1.0
Requires-Dist: gse-gsatmicro-utils>=3.1.0
Requires-Dist: prettytable>=3.11.0
Requires-Dist: pyftpdlib>=2.0.1
Requires-Dist: python-minifier>=2.11.3
Requires-Dist: tqdm>=4.66.6
